[
  {
    "title": "Le vieux chêne, branlant, mais star à Melen",
    "file": "article-vieux-chene.html",
    "rueId": "place-eglise",           
    "rueNom": "Place de l'église",
    "periode": "18e–20e siècle",
    "famille": null,
    "theme": "Patrimoine",
    "image": "images/vieux_chene.jpeg",
    "video": null
  },
  {
    "title": "Mini-révolution mélinoise pour le bac à l'eau de Reux",
    "file": "article-bac-reux.html",
    "rueId": "rue-reux",           
    "rueNom": "Rue Reux",
    "periode": "Début 20e siècle",
    "famille": null,
    "theme": "Vie quotidienne",
    "image": "images/bac_reux.jpeg",
    "video": null
  },
  {
    "title": "Une petite juive cachée rue Louis Pasteur",
    "file": "Article-petite-juive-cachee.html",
    "rueId": "rue-louis-pasteur",           
    "rueNom": "Rue Louis Pasteur",
    "periode": "Seconde Guerre mondiale",
    "famille": "Fafchamps",
    "theme": "Résistance",
    "image": "images/rue-louis-pasteur.jpeg",
    "video": null
  },
  {
    "title": "Le p'tit curé a aidé à sauver des enfants juifs",
    "file": "Article-ptit-cure-video.html",
    "rueId": null,   
    "rueNom": null,
    "periode": "Seconde Guerre mondiale",
    "famille": "Malvaux",
    "theme": "Résistance",
    "image": null,
    "video": null
  },
    {
    "title": "Un « petit Juif » caché qui chantait trop et près des Allemands",
    "file": "Article-petit-juif-chanter.html",
    "rueId": "parc-hauzeur",          
    "rueNom": "Rue du Parc Hauzeur",
    "periode": "1943-44",
    "famille": null,
    "theme": "Résistance",
    "image": "images/ferme-des-chenes.jpeg",
    "video": null
  },
  {
    "title": "Le vieux et le nouveau chêne",
    "file": "Article-vieux-nouveau-chene.html",
    "rueId": "place-eglise",          
    "rueNom": "Place de l'église",
    "periode": "18e–20e siècle",
    "famille": null,
    "theme": "Patrimoine",
    "image": "images/nouveau-chene-place-eglise.jpeg",
    "video": null
  },
  {
  "title": "Louis et Léonard, les petits Juifs cachés rue Haute",
  "file": "Article-louis-leonard.html",
  "rueId": "rue-haute",         
  "rueNom": "Rue Haute",
  "periode": "1943-44",
  "famille": null,
  "theme": "Résistance",
  "image": "images/rue-haute1.jpeg",
  "video": null
},
{
  "title": "Plus de pompe, mais des robiniers sur la place",
  "file": "Article-plus-de-pompe-robiniers.html",
  "rueId": "place-eglise",
  "rueNom": "Place de l'église",
  "periode": "Vers 1990",
  "famille": null,
  "theme": "Patrimoine",
  "image": "images/place-eglise-1990.jpeg",
  "video": null
},
{
  "title": "Le \"p'tit curé\" sourcillait face aux libérateurs américains et aux jeunes filles les plus libérées",
  "file": "Article-ptit-cure-liberateurs.html",
  "rueId": "presbytere",
  "rueNom": "Presbytère de Melen",
  "periode": "Seconde Guerre mondiale",
  "famille": "Malvaux",
  "theme": "Résistance",
  "image": "images/leon-malvaux-presbytere.jpeg",
  "video": null
},
{
  "title": "L'ancêtre classé de la place est vendu pour 10 francs",
  "file": "Article-ancetre-classe-place.html",
  "rueId": "place-eglise",
  "rueNom": "Place de l'église",
  "periode": "18e–20e siècle",
  "famille": "Chaineux",
  "theme": "Patrimoine",
  "image": "images/abattage-chene-liberte.jpeg",
  "video": null
},
{
  "title": "L'arbre Biscuit : un charmant charme au nom mystérieux",
  "file": "Article-arbre-biscuit.html",
  "rueId": "bois-halleux",
  "rueNom": "Bois de Halleux",
  "periode": "XXe siècle",
  "famille": null,
  "theme": "Patrimoine naturel",
  "image": "images/arbre-biscuit-bois-halleux.jpeg",
  "video": null
},
{
  "title": "L’amoureux avait de la galette et des biscuits",
  "file": "Article-amoureux-galette-biscuits.html",
  "rueId": "bois-halleux",
  "rueNom": "Bois de Halleux",
  "periode": "XVIIIe–XIXe siècle",
  "famille": null,
  "theme": "Légendes locales",
  "image": "images/arbre-biscuit-bois-halleux2.jpeg",
  "video": null
},
{
  "title": "Le coup de chapeau du « p’tit curé » qui offrait ses vélos",
  "file": "Article-coup-chapeau-petit-cure.html",
  "rueId": "presbytere",
  "rueNom": "Presbytère de Melen",
  "periode": "1943–1989",
  "famille": "Malvaux",
  "theme": "Figures locales",
  "image": "images/leon-malvaux-mobylette.jpeg",
  "video": null
},
{
  "title": "C’est grâce à ce « p’tit curé » qu’on a tant encensé le grand saint, à Melen",
  "file": "Article-saint-nicolas-petit-cure.html",
  "rueId": "presbytere",
  "rueNom": "Presbytère de Melen",
  "periode": "Seconde Guerre mondiale",
  "famille": "Malvaux",
  "theme": "Vie religieuse",
  "image": "images/leon-malvaux-1946.jpeg",
  "video": null
},
{
  "title": "Hit Hit Hourra : on ressuscite le tube qui a émerveillé les élèves mélinois durant 60 ans",
  "file": "article-hit-hit-hourra.html",
  "rueId": null,
  "rueNom": null,
  "periode": "XXe siècle",
  "famille": null,
  "theme": "Vie scolaire",
  "image": null,
  "video": "videos/hit-hit-hourra.mp4"
}






]
